woodwide/__init__.py
woodwide/_base_client.py
woodwide/_client.py
woodwide/_compat.py
woodwide/_constants.py
woodwide/_exceptions.py
woodwide/_files.py
woodwide/_models.py
woodwide/_qs.py
woodwide/_resource.py
woodwide/_response.py
woodwide/_streaming.py
woodwide/_types.py
woodwide/_version.py
woodwide/py.typed
woodwide/_utils/__init__.py
woodwide/_utils/_compat.py
woodwide/_utils/_datetime_parse.py
woodwide/_utils/_logs.py
woodwide/_utils/_proxy.py
woodwide/_utils/_reflection.py
woodwide/_utils/_resources_proxy.py
woodwide/_utils/_streams.py
woodwide/_utils/_sync.py
woodwide/_utils/_transform.py
woodwide/_utils/_typing.py
woodwide/_utils/_utils.py
woodwide/lib/.keep
woodwide/resources/__init__.py
woodwide/resources/auth.py
woodwide/resources/api/__init__.py
woodwide/resources/api/api.py
woodwide/resources/api/datasets.py
woodwide/resources/api/models/__init__.py
woodwide/resources/api/models/anomaly.py
woodwide/resources/api/models/clustering.py
woodwide/resources/api/models/embedding.py
woodwide/resources/api/models/factors.py
woodwide/resources/api/models/models.py
woodwide/resources/api/models/prediction.py
woodwide/types/__init__.py
woodwide/types/auth_retrieve_me_response.py
woodwide/types/api/__init__.py
woodwide/types/api/dataset_delete_params.py
woodwide/types/api/dataset_list_params.py
woodwide/types/api/dataset_list_response.py
woodwide/types/api/dataset_public.py
woodwide/types/api/dataset_retrieve_params.py
woodwide/types/api/dataset_upload_params.py
woodwide/types/api/model_list_response.py
woodwide/types/api/model_public.py
woodwide/types/api/model_retrieve_params.py
woodwide/types/api/schema.py
woodwide/types/api/models/__init__.py
woodwide/types/api/models/anomaly_infer_params.py
woodwide/types/api/models/anomaly_infer_response.py
woodwide/types/api/models/anomaly_train_params.py
woodwide/types/api/models/clustering_infer_params.py
woodwide/types/api/models/clustering_infer_response.py
woodwide/types/api/models/clustering_train_params.py
woodwide-0.7.0.dist-info/METADATA
woodwide-0.7.0.dist-info/WHEEL
woodwide-0.7.0.dist-info/licenses/LICENSE
woodwide-0.7.0.dist-info/RECORD
